{
  "1": {
    "answer":"one"
  },
  "2": {
    "answer":"two"
  },
  "3": {
    "answer":"three"
  },
  "4": {
    "answer":"four"
  },
  "5": {
    "answer":"five"
  },
  "6": {
    "answer":"six"
  },
  "7": {
    "answer":"seven"
  },
  "8": {
    "answer":"eight"
  },
  "9": {
    "answer":"nine"
  },
  "10": {
    "answer":"ten"
  },
  "11": {
    "answer":"eleven"
  },
  "12": {
    "answer":"twelve"
  },
  "13": {
    "answer":"thirteen"
  },
  "14": {
    "answer":"fourteen"
  },
  "15": {
    "answer":"fifteen"
  },
  "16": {
    "answer":"sixteen"
  },
  "17": {
    "answer":"seventeen"
  },
  "18": {
    "answer":"eighteen"
  },
  "19": {
    "answer":"nineteen"
  },
  "20": {
    "answer":"twenty"
  },
  "21": {
    "answer":"twenty-one"
  },
  "21": {
    "answer":"eleven"
  },
  "22": {
    "answer":"twelve"
  },
  "23": {
    "answer":"thirteen"
  },
  "24": {
    "answer":"fourteen"
  },
  "25": {
    "answer":"fifteen"
  },
  "26": {
    "answer":"sixteen"
  },
  "27": {
    "answer":"seventeen"
  },
  "28": {
    "answer":"eighteen"
  },
  "29": {
    "answer":"nineteen"
  },
  "30": {
    "answer":"twenty"
  }
}
